nonebot_plugin_fg/Segmentation.py
nonebot_plugin_fg/TextRank4Keyword.py
nonebot_plugin_fg/__init__.py
nonebot_plugin_fg/base.py
nonebot_plugin_fg/config.py
nonebot_plugin_fg/core.py
nonebot_plugin_fg/group_rule.py
nonebot_plugin_fg/record.py
nonebot_plugin_fg/stopwords.txt
nonebot_plugin_fg/util.py
nonebot_plugin_fg-2.0.2.dist-info/LICENSE
nonebot_plugin_fg-2.0.2.dist-info/METADATA
nonebot_plugin_fg-2.0.2.dist-info/WHEEL
nonebot_plugin_fg-2.0.2.dist-info/top_level.txt
nonebot_plugin_fg-2.0.2.dist-info/RECORD
