Metadata-Version: 2.1
Name: nonebot-plugin-fg
Version: 2.0.2
Summary: 一个基于Nonebot2的QQ群每日总结生成插件，可以根据每日的聊天信息生成每日热词
Home-page: https://github.com/mgsky1/FG-plugin
Author: mgsky1
Author-email: hzy@acmsmu.cn
License: UNKNOWN
Platform: UNKNOWN
Classifier: Programming Language :: Python :: 3.7
Classifier: License :: OSI Approved :: Apache Software License
Classifier: Operating System :: OS Independent
License-File: LICENSE
Requires-Dist: networkx (==2.6.3)
Requires-Dist: numpy (==1.22.1)
Requires-Dist: scipy (==1.7.3)
Requires-Dist: jieba (==0.42.1)
